[
  {
    "id": 1765742169551,
    "service": "Formatação de Windows",
    "name": "pedro henrique lima da costa ",
    "phone": "(21) 97680-5999",
    "address": "fxcghjk",
    "description": "",
    "created_at": "2025-12-14T19:56:09.551Z"
  },
  {
    "id": 1765742197003,
    "service": "Limpeza Interna e Troca de Pasta Térmica",
    "name": "pedro henrique lima da costa ",
    "phone": "(21) 97680-5999",
    "address": "fxcghjk",
    "description": "",
    "created_at": "2025-12-14T19:56:37.003Z"
  },
  {
    "id": 1765743109002,
    "service": "Backup e Recuperação de Dados",
    "name": "pedro henrique lima da costa ",
    "phone": "(21) 97680-5999",
    "address": "fxcghjk",
    "description": "",
    "created_at": "2025-12-14T20:11:49.004Z"
  }
]